{
	"animations": [
		{
			"offsets": [
				-7,
				10
			],
			"loop": false,
			"fps": 24,
			"anim": "singUP",
			"indices": [],
			"name": "SONICmoveUP"
		},
		{
			"offsets": [
				-168,
				-57
			],
			"loop": false,
			"fps": 24,
			"anim": "singRIGHT",
			"indices": [],
			"name": "SONICmoveRIGHT"
		},
		{
			"offsets": [
				-32,
				-154
			],
			"loop": false,
			"fps": 24,
			"anim": "singDOWN",
			"indices": [],
			"name": "SONICmoveDOWN"
		},
		{
			"offsets": [
				103,
				-11
			],
			"loop": false,
			"fps": 24,
			"anim": "singLEFT",
			"indices": [],
			"name": "SONICmoveLEFT"
		},
		{
			"loop": true,
			"offsets": [
				-90,
				-80
			],
			"anim": "idle",
			"fps": 24,
			"name": "SONICmoveIDLE",
			"indices": []
		},
		{
			"offsets": [
				-70,
				-38
			],
			"loop": false,
			"fps": 17,
			"anim": "singDOWN-alt",
			"indices": [],
			"name": "SONIClaugh"
		},
		{
			"loop": false,
			"offsets": [
				22,
				-60
			],
			"anim": "Getya",
			"fps": 21,
			"name": "sonicImmagetya",
			"indices": []
		}
	],
	"vocals_file": "",
	"no_antialiasing": false,
	"image": "characters/Sonic_EXE_kopia",
	"position": [
		0,
		0
	],
	"healthicon": "sonicexe",
	"flip_x": false,
	"healthbar_colors": [
		0,
		85,
		142
	],
	"camera_position": [
		10,
		50
	],
	"sing_duration": 4,
	"scale": 1.2,
	"_editor_isPlayer": false
}